[
  {
    "t": "2026-04-22T12:00:00.000Z",
    "twl": 4.7,
    "tide": 3.923,
    "surge": 0.8,
    "src_time": "202604221200"
  },
  {
    "t": "2026-04-22T13:00:00.000Z",
    "twl": 3.739,
    "tide": 3.022,
    "surge": 0.7,
    "src_time": "202604221300"
  },
  {
    "t": "2026-04-22T14:00:00.000Z",
    "twl": 2.807,
    "tide": 2.112,
    "surge": 0.7,
    "src_time": "202604221400"
  },
  {
    "t": "2026-04-22T15:00:00.000Z",
    "twl": 1.967,
    "tide": 1.15,
    "surge": 0.7,
    "src_time": "202604221500"
  },
  {
    "t": "2026-04-22T16:00:00.000Z",
    "twl": 1.269,
    "tide": 0.5,
    "surge": 0.7,
    "src_time": "202604221600"
  },
  {
    "t": "2026-04-22T17:00:00.000Z",
    "twl": 1.269,
    "tide": 0.905,
    "surge": 0.7,
    "src_time": "202604221700"
  },
  {
    "t": "2026-04-22T18:00:00.000Z",
    "twl": 2.919,
    "tide": 2.273,
    "surge": 0.6,
    "src_time": "202604221800"
  },
  {
    "t": "2026-04-22T19:00:00.000Z",
    "twl": 4.368,
    "tide": 3.679,
    "surge": 0.6,
    "src_time": "202604221900"
  },
  {
    "t": "2026-04-22T20:00:00.000Z",
    "twl": 5.448,
    "tide": 4.665,
    "surge": 0.5,
    "src_time": "202604222000"
  },
  {
    "t": "2026-04-22T21:00:00.000Z",
    "twl": 5.897,
    "tide": 5.198,
    "surge": 0.5,
    "src_time": "202604222100"
  },
  {
    "t": "2026-04-22T22:00:00.000Z",
    "twl": 5.648,
    "tide": 5.089,
    "surge": 0.5,
    "src_time": "202604222200"
  },
  {
    "t": "2026-04-22T23:00:00.000Z",
    "twl": 4.608,
    "tide": 4.424,
    "surge": 0.5,
    "src_time": "202604222300"
  },
  {
    "t": "2026-04-23T00:00:00.000Z",
    "twl": 3.578,
    "tide": 3.565,
    "surge": 0.5,
    "src_time": "202604230000"
  },
  {
    "t": "2026-04-23T01:00:00.000Z",
    "twl": 2.66,
    "tide": 2.696,
    "surge": 0.5,
    "src_time": "202604230100"
  },
  {
    "t": "2026-04-23T02:00:00.000Z",
    "twl": 1.781,
    "tide": 1.916,
    "surge": 0.5,
    "src_time": "202604230200"
  },
  {
    "t": "2026-04-23T03:00:00.000Z",
    "twl": 1.029,
    "tide": 1.24,
    "surge": 0.5,
    "src_time": "202604230300"
  },
  {
    "t": "2026-04-23T04:00:00.000Z",
    "twl": 0.478,
    "tide": 0.769,
    "surge": 0.5,
    "src_time": "202604230400"
  },
  {
    "t": "2026-04-23T05:00:00.000Z",
    "twl": 1.489,
    "tide": 1.103,
    "surge": 0.6,
    "src_time": "202604230500"
  },
  {
    "t": "2026-04-23T06:00:00.000Z",
    "twl": 3.319,
    "tide": 2.516,
    "surge": 0.5,
    "src_time": "202604230600"
  },
  {
    "t": "2026-04-23T07:00:00.000Z",
    "twl": 4.939,
    "tide": 4.201,
    "surge": 0.5,
    "src_time": "202604230700"
  },
  {
    "t": "2026-04-23T08:00:00.000Z",
    "twl": 6.149,
    "tide": 5.386,
    "surge": 0.5,
    "src_time": "202604230800"
  },
  {
    "t": "2026-04-23T09:00:00.000Z",
    "twl": 6.838,
    "tide": 6.032,
    "surge": 0.5,
    "src_time": "202604230900"
  },
  {
    "t": "2026-04-23T10:00:00.000Z",
    "twl": 7.038,
    "tide": 6.104,
    "surge": 0.5,
    "src_time": "202604231000"
  },
  {
    "t": "2026-04-23T11:00:00.000Z",
    "twl": 6.448,
    "tide": 5.576,
    "surge": 0.5,
    "src_time": "202604231100"
  },
  {
    "t": "2026-04-23T12:00:00.000Z",
    "twl": 5.389,
    "tide": 4.774,
    "surge": 0.5,
    "src_time": "202604231200"
  },
  {
    "t": "2026-04-23T13:00:00.000Z",
    "twl": 4.188,
    "tide": 3.936,
    "surge": 0.5,
    "src_time": "202604231300"
  },
  {
    "t": "2026-04-23T14:00:00.000Z",
    "twl": 3.178,
    "tide": 3.082,
    "surge": 0.5,
    "src_time": "202604231400"
  },
  {
    "t": "2026-04-23T15:00:00.000Z",
    "twl": 2.24,
    "tide": 2.179,
    "surge": 0.5,
    "src_time": "202604231500"
  },
  {
    "t": "2026-04-23T16:00:00.000Z",
    "twl": 1.42,
    "tide": 1.182,
    "surge": 0.5,
    "src_time": "202604231600"
  },
  {
    "t": "2026-04-23T17:00:00.000Z",
    "twl": 0.81,
    "tide": 0.546,
    "surge": 0.5,
    "src_time": "202604231700"
  },
  {
    "t": "2026-04-23T18:00:00.000Z",
    "twl": 1.269,
    "tide": 0.992,
    "surge": 0.6,
    "src_time": "202604231800"
  },
  {
    "t": "2026-04-23T19:00:00.000Z",
    "twl": 3.03,
    "tide": 2.288,
    "surge": 0.6,
    "src_time": "202604231900"
  },
  {
    "t": "2026-04-23T20:00:00.000Z",
    "twl": 4.427,
    "tide": 3.571,
    "surge": 0.6,
    "src_time": "202604232000"
  },
  {
    "t": "2026-04-23T21:00:00.000Z",
    "twl": 5.487,
    "tide": 4.543,
    "surge": 0.6,
    "src_time": "202604232100"
  },
  {
    "t": "2026-04-23T22:00:00.000Z",
    "twl": 6.067,
    "tide": 5.14,
    "surge": 0.6,
    "src_time": "202604232200"
  },
  {
    "t": "2026-04-23T23:00:00.000Z",
    "twl": 6.048,
    "tide": 5.099,
    "surge": 0.6,
    "src_time": "202604232300"
  },
  {
    "t": "2026-04-24T00:00:00.000Z",
    "twl": 5.297,
    "tide": 4.506,
    "surge": 0.6,
    "src_time": "202604240000"
  },
  {
    "t": "2026-04-24T01:00:00.000Z",
    "twl": 4.29,
    "tide": 3.701,
    "surge": 0.6,
    "src_time": "202604240100"
  },
  {
    "t": "2026-04-24T02:00:00.000Z",
    "twl": 3.24,
    "tide": 2.856,
    "surge": 0.6,
    "src_time": "202604240200"
  },
  {
    "t": "2026-04-24T03:00:00.000Z",
    "twl": 2.368,
    "tide": 2.075,
    "surge": 0.6,
    "src_time": "202604240300"
  },
  {
    "t": "2026-04-24T04:00:00.000Z",
    "twl": 1.538,
    "tide": 1.338,
    "surge": 0.6,
    "src_time": "202604240400"
  },
  {
    "t": "2026-04-24T05:00:00.000Z",
    "twl": 0.898,
    "tide": 0.805,
    "surge": 0.6,
    "src_time": "202604240500"
  },
  {
    "t": "2026-04-24T06:00:00.000Z",
    "twl": 1.38,
    "tide": 1.125,
    "surge": 0.6,
    "src_time": "202604240600"
  },
  {
    "t": "2026-04-24T07:00:00.000Z",
    "twl": 3.148,
    "tide": 2.452,
    "surge": 0.6,
    "src_time": "202604240700"
  },
  {
    "t": "2026-04-24T08:00:00.000Z",
    "twl": 4.657,
    "tide": 3.953,
    "surge": 0.6,
    "src_time": "202604240800"
  },
  {
    "t": "2026-04-24T09:00:00.000Z",
    "twl": 5.877,
    "tide": 5.045,
    "surge": 0.5,
    "src_time": "202604240900"
  },
  {
    "t": "2026-04-24T10:00:00.000Z",
    "twl": 6.589,
    "tide": 5.743,
    "surge": 0.5,
    "src_time": "202604241000"
  },
  {
    "t": "2026-04-24T11:00:00.000Z",
    "twl": 6.779,
    "tide": 5.907,
    "surge": 0.5,
    "src_time": "202604241100"
  },
  {
    "t": "2026-04-24T12:00:00.000Z",
    "twl": 6.238,
    "tide": 5.477,
    "surge": 0.5,
    "src_time": "202604241200"
  },
  {
    "t": "2026-04-24T13:00:00.000Z",
    "twl": 5.247,
    "tide": 4.767,
    "surge": 0.5,
    "src_time": "202604241300"
  },
  {
    "t": "2026-04-24T14:00:00.000Z",
    "twl": 4.109,
    "tide": 3.98,
    "surge": 0.5,
    "src_time": "202604241400"
  },
  {
    "t": "2026-04-24T15:00:00.000Z",
    "twl": 3.109,
    "tide": 3.141,
    "surge": 0.5,
    "src_time": "202604241500"
  },
  {
    "t": "2026-04-24T16:00:00.000Z",
    "twl": 2.23,
    "tide": 2.202,
    "surge": 0.5,
    "src_time": "202604241600"
  },
  {
    "t": "2026-04-24T17:00:00.000Z",
    "twl": 1.41,
    "tide": 1.148,
    "surge": 0.5,
    "src_time": "202604241700"
  },
  {
    "t": "2026-04-24T18:00:00.000Z",
    "twl": 0.81,
    "tide": 0.531,
    "surge": 0.6,
    "src_time": "202604241800"
  },
  {
    "t": "2026-04-24T19:00:00.000Z",
    "twl": 1.289,
    "tide": 1.012,
    "surge": 0.6,
    "src_time": "202604241900"
  },
  {
    "t": "2026-04-24T20:00:00.000Z",
    "twl": 3.119,
    "tide": 2.243,
    "surge": 0.6,
    "src_time": "202604242000"
  },
  {
    "t": "2026-04-24T21:00:00.000Z",
    "twl": 4.608,
    "tide": 3.467,
    "surge": 0.7,
    "src_time": "202604242100"
  },
  {
    "t": "2026-04-24T22:00:00.000Z",
    "twl": 5.917,
    "tide": 4.509,
    "surge": 0.7,
    "src_time": "202604242200"
  },
  {
    "t": "2026-04-24T23:00:00.000Z",
    "twl": 6.556,
    "tide": 5.208,
    "surge": 0.7,
    "src_time": "202604242300"
  },
  {
    "t": "2026-04-25T00:00:00.000Z",
    "twl": 6.658,
    "tide": 5.233,
    "surge": 0.7,
    "src_time": "202604250000"
  },
  {
    "t": "2026-04-25T01:00:00.000Z",
    "twl": 6.058,
    "tide": 4.694,
    "surge": 0.8,
    "src_time": "202604250100"
  },
  {
    "t": "2026-04-25T02:00:00.000Z",
    "twl": 5.018,
    "tide": 3.914,
    "surge": 0.8,
    "src_time": "202604250200"
  },
  {
    "t": "2026-04-25T03:00:00.000Z",
    "twl": 3.998,
    "tide": 3.061,
    "surge": 0.8,
    "src_time": "202604250300"
  },
  {
    "t": "2026-04-25T04:00:00.000Z",
    "twl": 3.079,
    "tide": 2.231,
    "surge": 0.9,
    "src_time": "202604250400"
  },
  {
    "t": "2026-04-25T05:00:00.000Z",
    "twl": 2.24,
    "tide": 1.391,
    "surge": 0.9,
    "src_time": "202604250500"
  },
  {
    "t": "2026-04-25T06:00:00.000Z",
    "twl": 1.669,
    "tide": 0.777,
    "surge": 1,
    "src_time": "202604250600"
  },
  {
    "t": "2026-04-25T07:00:00.000Z",
    "twl": 2.328,
    "tide": 1.065,
    "surge": 1,
    "src_time": "202604250700"
  },
  {
    "t": "2026-04-25T08:00:00.000Z",
    "twl": 4.08,
    "tide": 2.291,
    "surge": 1,
    "src_time": "202604250800"
  },
  {
    "t": "2026-04-25T09:00:00.000Z",
    "twl": 5.389,
    "tide": 3.653,
    "surge": 1,
    "src_time": "202604250900"
  },
  {
    "t": "2026-04-25T10:00:00.000Z",
    "twl": 6.428,
    "tide": 4.742,
    "surge": 1,
    "src_time": "202604251000"
  },
  {
    "t": "2026-04-25T11:00:00.000Z",
    "twl": 7.048,
    "tide": 5.548,
    "surge": 1,
    "src_time": "202604251100"
  },
  {
    "t": "2026-04-25T12:00:00.000Z",
    "twl": 7.248,
    "tide": 5.805,
    "surge": 1.2,
    "src_time": "202604251200"
  },
  {
    "t": "2026-04-25T13:00:00.000Z",
    "twl": 6.947,
    "tide": 5.45,
    "surge": 1.2,
    "src_time": "202604251300"
  },
  {
    "t": "2026-04-25T14:00:00.000Z",
    "twl": 6.159,
    "tide": 4.793,
    "surge": 1.3,
    "src_time": "202604251400"
  },
  {
    "t": "2026-04-25T15:00:00.000Z",
    "twl": 5.097,
    "tide": 4.012,
    "surge": 1.3,
    "src_time": "202604251500"
  },
  {
    "t": "2026-04-25T16:00:00.000Z",
    "twl": 4.149,
    "tide": 3.146,
    "surge": 1.3,
    "src_time": "202604251600"
  },
  {
    "t": "2026-04-25T17:00:00.000Z",
    "twl": 3.26,
    "tide": 2.146,
    "surge": 1.4,
    "src_time": "202604251700"
  },
  {
    "t": "2026-04-25T18:00:00.000Z",
    "twl": 2.469,
    "tide": 1.042,
    "surge": 1.5,
    "src_time": "202604251800"
  },
  {
    "t": "2026-04-25T19:00:00.000Z",
    "twl": 1.981,
    "tide": 0.467,
    "surge": 1.6,
    "src_time": "202604251900"
  },
  {
    "t": "2026-04-25T20:00:00.000Z",
    "twl": 2.568,
    "tide": 0.999,
    "surge": 1.6,
    "src_time": "202604252000"
  },
  {
    "t": "2026-04-25T21:00:00.000Z",
    "twl": 3.87,
    "tide": 2.206,
    "surge": 1.6,
    "src_time": "202604252100"
  },
  {
    "t": "2026-04-25T22:00:00.000Z",
    "twl": 5.218,
    "tide": 3.456,
    "surge": 1.6,
    "src_time": "202604252200"
  },
  {
    "t": "2026-04-25T23:00:00.000Z",
    "twl": 6.209,
    "tide": 4.618,
    "surge": 1.6,
    "src_time": "202604252300"
  },
  {
    "t": "2026-04-26T00:00:00.000Z",
    "twl": 6.828,
    "tide": 5.41,
    "surge": 1.5,
    "src_time": "202604260000"
  },
  {
    "t": "2026-04-26T01:00:00.000Z",
    "twl": 6.927,
    "tide": 5.468,
    "surge": 1.5,
    "src_time": "202604260100"
  },
  {
    "t": "2026-04-26T02:00:00.000Z",
    "twl": 6.389,
    "tide": 4.943,
    "surge": 1.5,
    "src_time": "202604260200"
  },
  {
    "t": "2026-04-26T03:00:00.000Z",
    "twl": 5.507,
    "tide": 4.142,
    "surge": 1.5,
    "src_time": "202604260300"
  },
  {
    "t": "2026-04-26T04:00:00.000Z",
    "twl": 4.48,
    "tide": 3.239,
    "surge": 1.5,
    "src_time": "202604260400"
  },
  {
    "t": "2026-04-26T05:00:00.000Z",
    "twl": 3.45,
    "tide": 2.329,
    "surge": 1.4,
    "src_time": "202604260500"
  },
  {
    "t": "2026-04-26T06:00:00.000Z",
    "twl": 2.538,
    "tide": 1.374,
    "surge": 1.4,
    "src_time": "202604260600"
  },
  {
    "t": "2026-04-26T07:00:00.000Z",
    "twl": 1.849,
    "tide": 0.684,
    "surge": 1.3,
    "src_time": "202604260700"
  },
  {
    "t": "2026-04-26T08:00:00.000Z",
    "twl": 1.59,
    "tide": 0.946,
    "surge": 1.3,
    "src_time": "202604260800"
  },
  {
    "t": "2026-04-26T09:00:00.000Z",
    "twl": 2.889,
    "tide": 2.098,
    "surge": 1.2,
    "src_time": "202604260900"
  },
  {
    "t": "2026-04-26T10:00:00.000Z",
    "twl": 4.3,
    "tide": 3.398,
    "surge": 1.1,
    "src_time": "202604261000"
  },
  {
    "t": "2026-04-26T11:00:00.000Z",
    "twl": 5.408,
    "tide": 4.555,
    "surge": 1.1,
    "src_time": "202604261100"
  },
  {
    "t": "2026-04-26T12:00:00.000Z",
    "twl": 6.179,
    "tide": 5.474,
    "surge": 1.1,
    "src_time": "202604261200"
  },
  {
    "t": "2026-04-26T13:00:00.000Z",
    "twl": 6.487,
    "tide": 5.791,
    "surge": 1.1,
    "src_time": "202604261300"
  },
  {
    "t": "2026-04-26T14:00:00.000Z",
    "twl": 6.317,
    "tide": 5.465,
    "surge": 1.1,
    "src_time": "202604261400"
  },
  {
    "t": "2026-04-26T15:00:00.000Z",
    "twl": 5.608,
    "tide": 4.802,
    "surge": 1.1,
    "src_time": "202604261500"
  },
  {
    "t": "2026-04-26T16:00:00.000Z",
    "twl": 4.657,
    "tide": 3.977,
    "surge": 1.1,
    "src_time": "202604261600"
  },
  {
    "t": "2026-04-26T17:00:00.000Z",
    "twl": 3.66,
    "tide": 3.064,
    "surge": 1.1,
    "src_time": "202604261700"
  },
  {
    "t": "2026-04-26T18:00:00.000Z",
    "twl": 2.768,
    "tide": 2.006,
    "surge": 1,
    "src_time": "202604261800"
  },
  {
    "t": "2026-04-26T19:00:00.000Z",
    "twl": 1.981,
    "tide": 0.882,
    "surge": 1,
    "src_time": "202604261900"
  },
  {
    "t": "2026-04-26T20:00:00.000Z",
    "twl": 1.269,
    "tide": 0.389,
    "surge": 1.1,
    "src_time": "202604262000"
  },
  {
    "t": "2026-04-26T21:00:00.000Z",
    "twl": 1.371,
    "tide": 1.016,
    "surge": 1.1,
    "src_time": "202604262100"
  },
  {
    "t": "2026-04-26T22:00:00.000Z",
    "twl": 3.178,
    "tide": 2.266,
    "surge": 1.1,
    "src_time": "202604262200"
  },
  {
    "t": "2026-04-26T23:00:00.000Z",
    "twl": 4.667,
    "tide": 3.602,
    "surge": 1.1,
    "src_time": "202604262300"
  },
  {
    "t": "2026-04-27T00:00:00.000Z",
    "twl": 5.887,
    "tide": 4.886,
    "surge": 1,
    "src_time": "202604270000"
  },
  {
    "t": "2026-04-27T01:00:00.000Z",
    "twl": 6.546,
    "tide": 5.72,
    "surge": 1,
    "src_time": "202604270100"
  },
  {
    "t": "2026-04-27T02:00:00.000Z",
    "twl": 6.868,
    "tide": 5.75,
    "surge": 1,
    "src_time": "202604270200"
  },
  {
    "t": "2026-04-27T03:00:00.000Z",
    "twl": 6.468,
    "tide": 5.176,
    "surge": 1,
    "src_time": "202604270300"
  },
  {
    "t": "2026-04-27T04:00:00.000Z",
    "twl": 5.53,
    "tide": 4.304,
    "surge": 1,
    "src_time": "202604270400"
  },
  {
    "t": "2026-04-27T05:00:00.000Z",
    "twl": 4.368,
    "tide": 3.331,
    "surge": 1,
    "src_time": "202604270500"
  },
  {
    "t": "2026-04-27T06:00:00.000Z",
    "twl": 3.368,
    "tide": 2.341,
    "surge": 1,
    "src_time": "202604270600"
  },
  {
    "t": "2026-04-27T07:00:00.000Z",
    "twl": 2.479,
    "tide": 1.276,
    "surge": 0.9,
    "src_time": "202604270700"
  },
  {
    "t": "2026-04-27T08:00:00.000Z",
    "twl": 1.728,
    "tide": 0.538,
    "surge": 0.9,
    "src_time": "202604270800"
  },
  {
    "t": "2026-04-27T09:00:00.000Z",
    "twl": 1.371,
    "tide": 0.818,
    "surge": 0.9,
    "src_time": "202604270900"
  },
  {
    "t": "2026-04-27T10:00:00.000Z",
    "twl": 2.669,
    "tide": 1.957,
    "surge": 0.8,
    "src_time": "202604271000"
  },
  {
    "t": "2026-04-27T11:00:00.000Z",
    "twl": 4.218,
    "tide": 3.265,
    "surge": 0.8,
    "src_time": "202604271100"
  },
  {
    "t": "2026-04-27T12:00:00.000Z",
    "twl": 5.457,
    "tide": 4.518,
    "surge": 0.8,
    "src_time": "202604271200"
  },
  {
    "t": "2026-04-27T13:00:00.000Z",
    "twl": 6.287,
    "tide": 5.518,
    "surge": 0.8,
    "src_time": "202604271300"
  },
  {
    "t": "2026-04-27T14:00:00.000Z",
    "twl": 6.678,
    "tide": 5.831,
    "surge": 0.8,
    "src_time": "202604271400"
  },
  {
    "t": "2026-04-27T15:00:00.000Z",
    "twl": 6.307,
    "tide": 5.461,
    "surge": 0.8,
    "src_time": "202604271500"
  },
  {
    "t": "2026-04-27T16:00:00.000Z",
    "twl": 5.329,
    "tide": 4.73,
    "surge": 0.7,
    "src_time": "202604271600"
  },
  {
    "t": "2026-04-27T17:00:00.000Z",
    "twl": 4.257,
    "tide": 3.841,
    "surge": 0.7,
    "src_time": "202604271700"
  },
  {
    "t": "2026-04-27T18:00:00.000Z",
    "twl": 3.331,
    "tide": 2.893,
    "surge": 0.7,
    "src_time": "202604271800"
  },
  {
    "t": "2026-04-27T19:00:00.000Z",
    "twl": 2.258,
    "tide": 1.799,
    "surge": 0.7,
    "src_time": "202604271900"
  },
  {
    "t": "2026-04-27T20:00:00.000Z",
    "twl": 1.179,
    "tide": 0.698,
    "surge": 0.7,
    "src_time": "202604272000"
  },
  {
    "t": "2026-04-27T21:00:00.000Z",
    "twl": 0.857,
    "tide": 0.355,
    "surge": 0.7,
    "src_time": "202604272100"
  },
  {
    "t": "2026-04-27T22:00:00.000Z",
    "twl": 1.665,
    "tide": 1.141,
    "surge": 0.7,
    "src_time": "202604272200"
  },
  {
    "t": "2026-04-27T23:00:00.000Z",
    "twl": 3.031,
    "tide": 2.486,
    "surge": 0.7,
    "src_time": "202604272300"
  },
  {
    "t": "2026-04-28T00:00:00.000Z",
    "twl": 4.491,
    "tide": 3.924,
    "surge": 0.7,
    "src_time": "202604280000"
  },
  {
    "t": "2026-04-28T01:00:00.000Z",
    "twl": 5.972,
    "tide": 5.284,
    "surge": 0.8,
    "src_time": "202604280100"
  },
  {
    "t": "2026-04-28T02:00:00.000Z",
    "twl": 6.785,
    "tide": 6.075,
    "surge": 0.8,
    "src_time": "202604280200"
  },
  {
    "t": "2026-04-28T03:00:00.000Z",
    "twl": 6.727,
    "tide": 5.996,
    "surge": 0.8,
    "src_time": "202604280300"
  },
  {
    "t": "2026-04-28T04:00:00.000Z",
    "twl": 6.062,
    "tide": 5.309,
    "surge": 0.8,
    "src_time": "202604280400"
  },
  {
    "t": "2026-04-28T05:00:00.000Z",
    "twl": 5.118,
    "tide": 4.344,
    "surge": 0.8,
    "src_time": "202604280500"
  },
  {
    "t": "2026-04-28T06:00:00.000Z",
    "twl": 4.09,
    "tide": 3.316,
    "surge": 0.8,
    "src_time": "202604280600"
  },
  {
    "t": "2026-04-28T07:00:00.000Z",
    "twl": 3.028,
    "tide": 2.254,
    "surge": 0.8,
    "src_time": "202604280700"
  },
  {
    "t": "2026-04-28T08:00:00.000Z",
    "twl": 1.777,
    "tide": 1.103,
    "surge": 0.7,
    "src_time": "202604280800"
  },
  {
    "t": "2026-04-28T09:00:00.000Z",
    "twl": 1.053,
    "tide": 0.379,
    "surge": 0.7,
    "src_time": "202604280900"
  },
  {
    "t": "2026-04-28T10:00:00.000Z",
    "twl": 1.424,
    "tide": 0.75,
    "surge": 0.7,
    "src_time": "202604281000"
  },
  {
    "t": "2026-04-28T11:00:00.000Z",
    "twl": 2.61,
    "tide": 1.936,
    "surge": 0.7,
    "src_time": "202604281100"
  },
  {
    "t": "2026-04-28T12:00:00.000Z",
    "twl": 3.966,
    "tide": 3.292,
    "surge": 0.7,
    "src_time": "202604281200"
  },
  {
    "t": "2026-04-28T13:00:00.000Z",
    "twl": 5.304,
    "tide": 4.63,
    "surge": 0.7,
    "src_time": "202604281300"
  },
  {
    "t": "2026-04-28T14:00:00.000Z",
    "twl": 6.311,
    "tide": 5.637,
    "surge": 0.7,
    "src_time": "202604281400"
  },
  {
    "t": "2026-04-28T15:00:00.000Z",
    "twl": 6.531,
    "tide": 5.857,
    "surge": 0.7,
    "src_time": "202604281500"
  },
  {
    "t": "2026-04-28T16:00:00.000Z",
    "twl": 6.047,
    "tide": 5.373,
    "surge": 0.7,
    "src_time": "202604281600"
  },
  {
    "t": "2026-04-28T17:00:00.000Z",
    "twl": 5.22,
    "tide": 4.546,
    "surge": 0.7,
    "src_time": "202604281700"
  },
  {
    "t": "2026-04-28T18:00:00.000Z",
    "twl": 4.285,
    "tide": 3.611,
    "surge": 0.7,
    "src_time": "202604281800"
  },
  {
    "t": "2026-04-28T19:00:00.000Z",
    "twl": 3.324,
    "tide": 2.65,
    "surge": 0.7,
    "src_time": "202604281900"
  },
  {
    "t": "2026-04-28T20:00:00.000Z",
    "twl": 2.223,
    "tide": 1.549,
    "surge": 0.7,
    "src_time": "202604282000"
  },
  {
    "t": "2026-04-28T21:00:00.000Z",
    "twl": 1.216,
    "tide": 0.542,
    "surge": 0.7,
    "src_time": "202604282100"
  },
  {
    "t": "2026-04-28T22:00:00.000Z",
    "twl": 1.107,
    "tide": 0.433,
    "surge": 0.7,
    "src_time": "202604282200"
  },
  {
    "t": "2026-04-28T23:00:00.000Z",
    "twl": 2.202,
    "tide": 1.428,
    "surge": 0.8,
    "src_time": "202604282300"
  },
  {
    "t": "2026-04-29T00:00:00.000Z",
    "twl": 3.657,
    "tide": 2.883,
    "surge": 0.8,
    "src_time": "202604290000"
  },
  {
    "t": "2026-04-29T01:00:00.000Z",
    "twl": 5.172,
    "tide": 4.398,
    "surge": 0.8,
    "src_time": "202604290100"
  },
  {
    "t": "2026-04-29T02:00:00.000Z",
    "twl": 6.522,
    "tide": 5.748,
    "surge": 0.8,
    "src_time": "202604290200"
  },
  {
    "t": "2026-04-29T03:00:00.000Z",
    "twl": 7.161,
    "tide": 6.387,
    "surge": 0.8,
    "src_time": "202604290300"
  },
  {
    "t": "2026-04-29T04:00:00.000Z",
    "twl": 6.99,
    "tide": 6.116,
    "surge": 0.9,
    "src_time": "202604290400"
  },
  {
    "t": "2026-04-29T05:00:00.000Z",
    "twl": 6.163,
    "tide": 5.289,
    "surge": 0.9,
    "src_time": "202604290500"
  },
  {
    "t": "2026-04-29T06:00:00.000Z",
    "twl": 5.124,
    "tide": 4.25,
    "surge": 0.9,
    "src_time": "202604290600"
  },
  {
    "t": "2026-04-29T07:00:00.000Z",
    "twl": 3.962,
    "tide": 3.188,
    "surge": 0.8,
    "src_time": "202604290700"
  },
  {
    "t": "2026-04-29T08:00:00.000Z",
    "twl": 2.844,
    "tide": 2.07,
    "surge": 0.8,
    "src_time": "202604290800"
  },
  {
    "t": "2026-04-29T09:00:00.000Z",
    "twl": 1.659,
    "tide": 0.885,
    "surge": 0.8,
    "src_time": "202604290900"
  },
  {
    "t": "2026-04-29T10:00:00.000Z",
    "twl": 1.14,
    "tide": 0.266,
    "surge": 0.9,
    "src_time": "202604291000"
  },
  {
    "t": "2026-04-29T11:00:00.000Z",
    "twl": 1.672,
    "tide": 0.798,
    "surge": 0.9,
    "src_time": "202604291100"
  },
  {
    "t": "2026-04-29T12:00:00.000Z",
    "twl": 2.943,
    "tide": 2.069,
    "surge": 0.9,
    "src_time": "202604291200"
  },
  {
    "t": "2026-04-29T13:00:00.000Z",
    "twl": 4.354,
    "tide": 3.48,
    "surge": 0.9,
    "src_time": "202604291300"
  },
  {
    "t": "2026-04-29T14:00:00.000Z",
    "twl": 5.724,
    "tide": 4.85,
    "surge": 0.9,
    "src_time": "202604291400"
  },
  {
    "t": "2026-04-29T15:00:00.000Z",
    "twl": 6.636,
    "tide": 5.762,
    "surge": 0.9,
    "src_time": "202604291500"
  },
  {
    "t": "2026-04-29T16:00:00.000Z",
    "twl": 6.675,
    "tide": 5.801,
    "surge": 0.9,
    "src_time": "202604291600"
  },
  {
    "t": "2026-04-29T17:00:00.000Z",
    "twl": 6.141,
    "tide": 5.167,
    "surge": 1,
    "src_time": "202604291700"
  },
  {
    "t": "2026-04-29T18:00:00.000Z",
    "twl": 5.234,
    "tide": 4.26,
    "surge": 1,
    "src_time": "202604291800"
  },
  {
    "t": "2026-04-29T19:00:00.000Z",
    "twl": 4.281,
    "tide": 3.307,
    "surge": 1,
    "src_time": "202604291900"
  },
  {
    "t": "2026-04-29T20:00:00.000Z",
    "twl": 3.33,
    "tide": 2.356,
    "surge": 1,
    "src_time": "202604292000"
  },
  {
    "t": "2026-04-29T21:00:00.000Z",
    "twl": 2.367,
    "tide": 1.293,
    "surge": 1.1,
    "src_time": "202604292100"
  },
  {
    "t": "2026-04-29T22:00:00.000Z",
    "twl": 1.543,
    "tide": 0.469,
    "surge": 1.1,
    "src_time": "202604292200"
  },
  {
    "t": "2026-04-29T23:00:00.000Z",
    "twl": 1.841,
    "tide": 0.667,
    "surge": 1.2,
    "src_time": "202604292300"
  },
  {
    "t": "2026-04-30T00:00:00.000Z",
    "twl": 3.064,
    "tide": 1.89,
    "surge": 1.2,
    "src_time": "202604300000"
  },
  {
    "t": "2026-04-30T01:00:00.000Z",
    "twl": 4.611,
    "tide": 3.437,
    "surge": 1.2,
    "src_time": "202604300100"
  },
  {
    "t": "2026-04-30T02:00:00.000Z",
    "twl": 6.138,
    "tide": 4.964,
    "surge": 1.2,
    "src_time": "202604300200"
  },
  {
    "t": "2026-04-30T03:00:00.000Z",
    "twl": 7.356,
    "tide": 6.182,
    "surge": 1.2,
    "src_time": "202604300300"
  },
  {
    "t": "2026-04-30T04:00:00.000Z",
    "twl": 7.636,
    "tide": 6.562,
    "surge": 1.1,
    "src_time": "202604300400"
  },
  {
    "t": "2026-04-30T05:00:00.000Z",
    "twl": 7.137,
    "tide": 6.063,
    "surge": 1.1,
    "src_time": "202604300500"
  },
  {
    "t": "2026-04-30T06:00:00.000Z",
    "twl": 6.188,
    "tide": 5.114,
    "surge": 1.1,
    "src_time": "202604300600"
  },
  {
    "t": "2026-04-30T07:00:00.000Z",
    "twl": 5.005,
    "tide": 4.031,
    "surge": 1,
    "src_time": "202604300700"
  },
  {
    "t": "2026-04-30T08:00:00.000Z",
    "twl": 3.93,
    "tide": 2.956,
    "surge": 1,
    "src_time": "202604300800"
  },
  {
    "t": "2026-04-30T09:00:00.000Z",
    "twl": 2.685,
    "tide": 1.811,
    "surge": 0.9,
    "src_time": "202604300900"
  },
  {
    "t": "2026-04-30T10:00:00.000Z",
    "twl": 1.544,
    "tide": 0.67,
    "surge": 0.9,
    "src_time": "202604301000"
  },
  {
    "t": "2026-04-30T11:00:00.000Z",
    "twl": 1.022,
    "tide": 0.248,
    "surge": 0.8,
    "src_time": "202604301100"
  },
  {
    "t": "2026-04-30T12:00:00.000Z",
    "twl": 1.766,
    "tide": 0.992,
    "surge": 0.8,
    "src_time": "202604301200"
  },
  {
    "t": "2026-04-30T13:00:00.000Z",
    "twl": 3.032,
    "tide": 2.358,
    "surge": 0.7,
    "src_time": "202604301300"
  },
  {
    "t": "2026-04-30T14:00:00.000Z",
    "twl": 4.371,
    "tide": 3.797,
    "surge": 0.6,
    "src_time": "202604301400"
  },
  {
    "t": "2026-04-30T15:00:00.000Z",
    "twl": 5.68,
    "tide": 5.106,
    "surge": 0.6,
    "src_time": "202604301500"
  },
  {
    "t": "2026-04-30T16:00:00.000Z",
    "twl": 6.289,
    "tide": 5.815,
    "surge": 0.5,
    "src_time": "202604301600"
  },
  {
    "t": "2026-04-30T17:00:00.000Z",
    "twl": 5.999,
    "tide": 5.625,
    "surge": 0.4,
    "src_time": "202604301700"
  },
  {
    "t": "2026-04-30T18:00:00.000Z",
    "twl": 5.229,
    "tide": 4.855,
    "surge": 0.4,
    "src_time": "202604301800"
  },
  {
    "t": "2026-04-30T19:00:00.000Z",
    "twl": 4.269,
    "tide": 3.895,
    "surge": 0.4,
    "src_time": "202604301900"
  },
  {
    "t": "2026-04-30T20:00:00.000Z",
    "twl": 3.322,
    "tide": 2.948,
    "surge": 0.4,
    "src_time": "202604302000"
  },
  {
    "t": "2026-04-30T21:00:00.000Z",
    "twl": 2.408,
    "tide": 2.034,
    "surge": 0.4,
    "src_time": "202604302100"
  },
  {
    "t": "2026-04-30T22:00:00.000Z",
    "twl": 1.447,
    "tide": 1.073,
    "surge": 0.4,
    "src_time": "202604302200"
  },
  {
    "t": "2026-04-30T23:00:00.000Z",
    "twl": 0.892,
    "tide": 0.518,
    "surge": 0.4,
    "src_time": "202604302300"
  },
  {
    "t": "2026-05-01T00:00:00.000Z",
    "twl": 1.441,
    "tide": 1.067,
    "surge": 0.4,
    "src_time": "202605010000"
  },
  {
    "t": "2026-05-01T01:00:00.000Z",
    "twl": 2.978,
    "tide": 2.504,
    "surge": 0.5,
    "src_time": "202605010100"
  },
  {
    "t": "2026-05-01T02:00:00.000Z",
    "twl": 4.566,
    "tide": 4.092,
    "surge": 0.5,
    "src_time": "202605010200"
  },
  {
    "t": "2026-05-01T03:00:00.000Z",
    "twl": 6,
    "tide": 5.526,
    "surge": 0.5,
    "src_time": "202605010300"
  },
  {
    "t": "2026-05-01T04:00:00.000Z",
    "twl": 6.965,
    "tide": 6.491,
    "surge": 0.5,
    "src_time": "202605010400"
  },
  {
    "t": "2026-05-01T05:00:00.000Z",
    "twl": 7.027,
    "tide": 6.553,
    "surge": 0.5,
    "src_time": "202605010500"
  },
  {
    "t": "2026-05-01T06:00:00.000Z",
    "twl": 6.316,
    "tide": 5.842,
    "surge": 0.5,
    "src_time": "202605010600"
  },
  {
    "t": "2026-05-01T07:00:00.000Z",
    "twl": 5.279,
    "tide": 4.805,
    "surge": 0.5,
    "src_time": "202605010700"
  },
  {
    "t": "2026-05-01T08:00:00.000Z",
    "twl": 4.079,
    "tide": 3.705,
    "surge": 0.4,
    "src_time": "202605010800"
  },
  {
    "t": "2026-05-01T09:00:00.000Z",
    "twl": 3.015,
    "tide": 2.641,
    "surge": 0.4,
    "src_time": "202605010900"
  },
  {
    "t": "2026-05-01T10:00:00.000Z",
    "twl": 1.892,
    "tide": 1.518,
    "surge": 0.4,
    "src_time": "202605011000"
  },
  {
    "t": "2026-05-01T11:00:00.000Z",
    "twl": 0.879,
    "tide": 0.505,
    "surge": 0.4,
    "src_time": "202605011100"
  },
  {
    "t": "2026-05-01T12:00:00.000Z",
    "twl": 0.731,
    "tide": 0.357,
    "surge": 0.4,
    "src_time": "202605011200"
  },
  {
    "t": "2026-05-01T13:00:00.000Z",
    "twl": 1.711,
    "tide": 1.337,
    "surge": 0.4,
    "src_time": "202605011300"
  },
  {
    "t": "2026-05-01T14:00:00.000Z",
    "twl": 3.151,
    "tide": 2.777,
    "surge": 0.4,
    "src_time": "202605011400"
  },
  {
    "t": "2026-05-01T15:00:00.000Z",
    "twl": 4.547,
    "tide": 4.173,
    "surge": 0.4,
    "src_time": "202605011500"
  },
  {
    "t": "2026-05-01T16:00:00.000Z",
    "twl": 5.688,
    "tide": 5.314,
    "surge": 0.4,
    "src_time": "202605011600"
  },
  {
    "t": "2026-05-01T17:00:00.000Z",
    "twl": 6.126,
    "tide": 5.752,
    "surge": 0.4,
    "src_time": "202605011700"
  },
  {
    "t": "2026-05-01T18:00:00.000Z",
    "twl": 5.711,
    "tide": 5.337,
    "surge": 0.4,
    "src_time": "202605011800"
  }
]
